resnap/__init__.py
resnap/decorators.py
resnap/exceptions.py
resnap/factory.py
resnap/py.typed
resnap/settings.py
resnap/version.py
resnap/boto/__init__.py
resnap/boto/client.py
resnap/boto/config.py
resnap/boto/connection.py
resnap/boto/dataframes.py
resnap/boto/py.typed
resnap/boto/tools.py
resnap/helpers/__init__.py
resnap/helpers/config.py
resnap/helpers/constants.py
resnap/helpers/context.py
resnap/helpers/metadata.py
resnap/helpers/py.typed
resnap/helpers/results_retriever.py
resnap/helpers/signature.py
resnap/helpers/singleton.py
resnap/helpers/ssl.py
resnap/helpers/status.py
resnap/helpers/time_utils.py
resnap/helpers/utils.py
resnap/services/__init__.py
resnap/services/boto_service.py
resnap/services/local_service.py
resnap/services/py.typed
resnap/services/service.py
resnap-0.4.0.dist-info/METADATA
resnap-0.4.0.dist-info/WHEEL
resnap-0.4.0.dist-info/licenses/LICENSE
resnap-0.4.0.dist-info/RECORD
