Metadata-Version: 2.4
Name: resnap
Version: 0.4.0
Summary: A Python library that captures and replays function results to save time, boost performance.
Project-URL: Repository, https://github.com/gloaguen-evan/resnap
Project-URL: Changelog, https://github.com/gloaguen-evan/resnap/releases
Project-URL: Issues, https://github.com/gloaguen-evan/resnap/issues
Author-email: Evan Gloaguen <evan.gloaguen@gmail.com>
License-Expression: MIT
License-File: LICENSE
Keywords: cache,checkpoint,function,method,python,results,save,snapshot
Classifier: Development Status :: 3 - Alpha
Classifier: Intended Audience :: Developers
Classifier: License :: OSI Approved :: MIT License
Classifier: Programming Language :: Python
Classifier: Programming Language :: Python :: 3
Classifier: Programming Language :: Python :: 3.10
Classifier: Programming Language :: Python :: 3.11
Classifier: Programming Language :: Python :: 3.12
Classifier: Topic :: Software Development :: Libraries
Requires-Python: <3.13,>=3.10
Requires-Dist: pandas[pyarrow]>=2.2.3
Requires-Dist: pydantic>=2.11.3
Requires-Dist: pyyaml>=6.0.2
Requires-Dist: toml>=0.10.2
